{
    "info": {
        "caseField": "2",
        "detailField": "6",
        "trailField": "1",
        "caseNm": "성폭력범죄의처벌등에관한특례법위반(주거침입강간)",
        "courtNm": "서울북부지방법원",
        "judmnAdjuDe": "2021. 08. 13.",
        "caseNo": "2021고합195",
        "relateLaword": [
            "성폭력범죄의 처벌 등에 관한 특례법 제15조",
            "성폭력범죄의 처벌 등에 관한 특례법 제3조",
            "형법 제319조",
            "형법 제297조",
            "형법 제25조",
            "형법 제55조",
            "형법 제53조",
            "형법 제55조",
            "형법 제62조",
            "성폭력범죄의 처벌 등에 관한 특례법 제47조",
            "성폭력범죄의 처벌 등에 관한 특례법 제49조",
            "아동·청소년의 성보호에 관한 법률 제49조",
            "아동·청소년의 성보호에 관한 법률 제50조",
            "아동·청소년의 성보호에 관한 법률 제56조",
            "장애인복지법 제59조",
            "성폭력범죄의 처벌 등에 관한 특례법 제42조",
            "성폭력범죄의 처벌 등에 관한 특례법 제43조"
        ],
        "qotatPrcdnt": []
    },
    "concerned": {
        "acusr": "4",
        "dedat": "1"
    },
    "org": {
        "orgJdgmnCourtNm": "",
        "orgJdgmnAdjuDe": "",
        "orgJdgmnCaseNo": ""
    },
    "disposal": {
        "disposalform": "6",
        "disposalcontent": [
            "피고인을 징역 3년에 처한다.",
            "다만, 이 판결 확정일로부터 4년간 위 형의 집행을 유예한다.",
            "피고인에 대하여 40시간의 성폭력 치료강의 수강을 명한다.",
            "피고인에 대하여 아동·청소년 관련기관 등과 장애인복지시설에 각 3년간 취업제한을 명한다."
        ]
    },
    "mentionedItems": {
        "rqestObjet": [
            "피고인을 징역 3년에 처한다.",
            "다만, 이 판결 확정일로부터 4년간 위 형의 집행을 유예한다.",
            "피고인에 대하여 40시간의 성폭력 치료강의 수강을 명한다.",
            "피고인에 대하여 아동, 청소년 관련기관 등과 장애인복지시설에 각 3년간 취업제한을 명한다."
        ]
    },
    "assrs": {
        "acusrAssrs": [],
        "dedatAssrs": [
            "피고인이 판시 기재와 같은 행위를 한 사실은 있으나, 피고인은 이 사건 당시 용변을 보기 위해 여자화장실에 들어간 것일 뿐 피해자를 강간할 목적이 없었고, 방실침입에 해당한다고 볼 수도 없으므로 주거침입강간죄가 성립하지 않는다."
        ]
    },
    "facts": {
        "bsisFacts": [
            "피고인은 2020.11.14.03:40경 0000 'C' 술집의 외부 복도에 있는 여자 화장실에서, 피해자 D(여, 26세)이 용변을 보기 위해 화장실로 들어가는 것을 보고 피해자를 강간할 것을 마음먹고 따라 들어가, 피해자가 들어간 용변칸 앞에서 바지와 팬티를 내린 상태로 피고인의 성기를 노출한 채 피해자를 기다리고 있다가, 피해자가 용변을 마치고 용변칸에서 나오려고 하자 피해자를 안으로 밀고 들어가 용변칸 문을 시정하였다.",
            "그러고는 피해자를 향해 '조용히 하라'는 손짓 한 후, 손으로 피해자의 머리카락을 잡은 상태로 피해자의 머리를 용변칸의 벽에 강한 힘으로 밀어 벽에 피해자의 머리를 수차례 부딪치게 하여 피해자의 반항을 억압한 다음, 피해자에게 \"한 번만\" 이라고 말하면서 손으로 피해자의 가슴을 만지고, 계속하여 피해자를 강간하려고 하였으나, 피해자가 발로 피해자를 걷어차며 완강히 저항하면서 화장실 밖으로 도망쳐 그 뜻을 이루지 못하고 미수에 그쳤다.",
            "피고인은 피해자가 점유하는 방실에 침입하여 피해자를 강간하려고 하였으나 미수에 그쳤다"
        ]
    },
    "dcss": {
        "courtDcss": [
            "피고인이 강간의 고의로 피해자가 점유하는 여자화장실 용변칸에 침입하여 피해자를 강간하려다가 미수에 그친 사실을 인정할 수 있다.",
            "따라서 피고인과 변호인의 주장은 받아들이지 않는다.",
            "피해자가 여자화장실 용변칸 안에서 나오려고 문을 열었을 당시 피고인은 바지와 팬티를 내린 상태로 성기를 노출한 채 용변칸 안으로 피해자를 밀고 들어가 문을 닫고 피해자의 머리를 벽에 밀어 부딪히게 하는 등으로 반항을 억압하고 \"한 번만\"이라고 말하며 피해자의 가슴을 만지는 등의 행위를 하였다.",
            "피고인이 성기를 노출한 상태에서 \"한 번만\"이라고 말한 것은 성관계를 하자는 의미로 보이고, 이러한 피고인의 행동과 피해자에게 한 말, 범행 당시의 상황 등을 고려하면 피고인에게 피해자의 반항을 억압하여 강간하려는 고의가 있었다고 봄이 상당하다.",
            "피고인이 들어간 여자화장실의 경우 여성이나 유아 등의 사용이 허용될 뿐, 성인 남성의 출입은 원칙상 허용되지 않는다.",
            "더욱이 피고인은 여자화장실 내부에서 피해자가 용변칸의 문을 열고 나오자 피고인의 성기를 노출한 채 용변칸 안으로 피해자를 밀고 들어가 범행을 시도하였다.",
            "이와 같이 성인 남성이 강간 등 범죄의 목적으로 여자화장실의 용변칸에 들어가는 것이 허용되지 아니함에는 의문의 여지가 없고, 피고인의 이러한 행위는 피해자가 점유하는 방실에 침입한 경우에 해당한다고 볼 수 있다.",
            "피고인이 피해자가 여자화장실에 들어가고 5분가량이 지난 후에 용변을 보기위해 여자화장실에 들어갔던 것이라고 하더라도, 위와 같이 피해자를 발견하고 성기를 노출한 채 용변칸 안으로 밀고 들어가 문을 닫고 피해자를 강간하려고 한 이상, 강간의 고의로 피해자가 점유하는 방실을 침입한 것이 아니라고 볼 수는 없다.",
            "피고인이 피해자가 있는 화장실의 용변칸 안으로 들어가 피해자를 강간하려다가 미수에 그친 것으로 범행 내용과 경위 등에 비추어 죄질이 좋지 않은 점, 피해자는 이 사건 범행으로 상당한 정신적 충격과 성적 수치심을 느꼈을 것으로 보이는 점 등은 피고인에게 불리한 정상이다.",
            "피고인이 이 사건 범행을 인정하며 반성하고 있는 점, 다행히 이 사건 강간 범행이 미수에 그친 점, 피고인이 피해자에게 700만 원을 지급하고 합의하여 피해자가 피고인에 대한 처벌을 원하지 않고 있는 점, 피고인이 이 사건 이전에 형사처벌을 받은 전력이 없는 점, ",
            "피고인은 과거 뇌수술을 받고 현재까지도 뇌전증 등으로 건강이 좋지 못한 것으로 보이는 점, 피고인의 부모가 피고인에 대한 지도를 다짐하며 선처를 탄원하고 있는 점 등은 피고인에게 유리한 정상이다.",
            "피고인의 나이, 성행, 환경, 가족관계, 범행의 동기, 범행의 수단과 결과, 범행 후의 정황 등 이 사건 변론에 나타난 모든 양형 요소를 고려하여 주문과 같이 형을 정한다."
        ]
    },
    "close": {
        "cnclsns": [
            "피고인을 징역 3년에 처한다.",
            "다만, 이 판결 확정일로부터 4년간 위 형의 집행을 유예한다.",
            "피고인에 대하여 40시간의 성폭력 치료강의 수강을 명한다.",
            "피고인에 대하여 아동·청소년 관련기관 등과 장애인복지시설에 각 3년간 취업제한을 명한다."
        ]
    }
}