{
    "info": {
        "caseField": "3",
        "detailField": "5",
        "trailField": "1",
        "caseNm": "부당해고 및 부당노동행위 구제재심판정취소",
        "courtNm": "대전지방법원",
        "judmnAdjuDe": "2017. 12. 06.",
        "caseNo": "2016구합102893",
        "relateLaword": [
            "근로기준법제23조",
            "근로기준법 제24조",
            "근로기준법 제30조",
            "근로기준법 제31조"
        ],
        "qotatPrcdnt": [
            "대법원 1991. 8. 9. 선고 91다15225판결, 1994. 11. 18. 선고 93다18938 판결",
            "대법원 2001. 7. 27. 선고 99두2680 판결",
            "대법원 2002. 3. 29. 선고 2000두8455 판결",
            "대법원 2002. 3. 26. 선고 2000다3347 판결",
            "대법원 1995. 9. 29. 선고 94다54245 판결",
            "대법원 1994. 6. 28. 선고 93다33173 판결",
            "대법원 1996. 4. 26. 선고95누1972 판결",
            "부산2015부해642/부노102 병합",
            "중앙2016부해120/부노22 병합"
        ]
    },
    "concerned": {
        "acusr": "1",
        "dedat": "1"
    },
    "org": {
        "orgJdgmnCourtNm": "",
        "orgJdgmnAdjuDe": "",
        "orgJdgmnCaseNo": ""
    },
    "disposal": {
        "disposalform": "10",
        "disposalcontent": [
            "원고의 청구를 기각한다.",
            "소송비용은 원고가 부담한다.",
            "소외 1과 소외 5가 체결한계약은 영업양도계약에 해당한다. ",
            "원고의 이 부분 주장은 이유 없다.",
            "소외 5가 소외 1에 대하여 ㅇㅇ요양병원의 영업부문 전부를 양도하였다고 봄이 상당하다. ",
            "원고의 이 부분 주장도 이유 없다.",
            "소외 1이 이 사건 근로자1,2의 고용승계를 거부하고, 이 사건 근로자3을 해고한 것은 부당해고에 해당한다. ",
            "원고의 이 부분 주장은 이유 없다.",
            "원고가 이 사건 병원의 영업을 양수하면서 이 사건 근로자들과의 근로관계가 승계되었다고 봄이 상당함에도 정당한 사유 없이 이 사건 근로자들의고용승계 요구를 거부한 것은 부당해고에 해당한다.",
            "원고의 이 부분 주장은 이유 없다.",
            "원고가 이 사건 근로자들의 고용승계를 거부한 것은 노동조합 및 노동관계조정법 제81조 제1호에 따른 불이익 취급의 부당노동행위에 해당한다. ",
            "원고의 이 부분 주장은 이유 없다."
        ]
    },
    "mentionedItems": {
        "rqestObjet": [
            "000가 2016. 5. 17. 원고와 소외 2, 소외 3, 소외 4, 000 사이의 2016부해120/부노22 병합 부당해고 및 부당노동행위 구제 재심신청사건에 관하여 한 재심판정을 취소한다."
        ]
    },
    "assrs": {
        "acusrAssrs": [
            "소외 1은 종래 조직을 해체하고 새롭게 조직을 구성하여 이 사건 병원의 영업을 개시한 것으로서 소외 5와 소외 1 사이에 체결한계약은 영업양도로 볼 수 없고, 설사 영업양도라 하더라도 행정지원부서와 물리치료실 등 정형외과 병원 영업에 필요한 부문을 제외한 일부양도에 해당한다.",
            "그렇다면 응급차기사인 이 사건 근로자1은 만성기 병원이어서 응급실이 필요 없는 이 사건 병원이 아닌 소외 5와 근로관계가 유지되어야 하고, 물리치료실 실장인 이 사건 근로자2는 소외 5가 같이 근무할 것을 제안하였음에도 이를 거부하였으므로 자의에 의하여 근로관계가 단절된 것이다.",
            "이 사건 근로자들은 원고가 이 사건 병원 영업을 양수할 당시 재직 중인 근로자들이 아니었고, 원고는 영업양수 당시 이 사건 각해고에 대해 다툼이 있는 사실을 알았을 뿐 해고가 무효임을 알지 못하였으며, 영업양수 이전에 이미 판결을 통하여 당해 해고가 무효임이 객관적으로 명확하게 된 경우도 아니므로, 이 사건 근로자들은 고용승계 대상 근로자에 해당하지 않는다.",
            "일반인인 원고가 소외 5와 소외 1이 체결한 계약의 법적성격에 대하여 판단하는 것은 어렵고, 중앙노동위원회가 인용하는 일부사실(원고가 노동조합 탈퇴를 강요했다는 사실)에 관한 부당노동행위 혐의에 관하여도 혐의없음의 불기소처분을 받았다.",
            "원고에게 부당노동행위의 의사가 있었다고 볼 수 없다.",
            "원고는 이에 대하여, 소외 1이 이 사건 병원의 영업을 양도받은 것이라고 하더라도 소외 5가 정형외과인 ○○△△병원을 개원 운영하기 위하여 소외 1과 ○○△△요양병원의 행정지원부서 조직 및 실장, 일부 근로자들에 대한 고용승계 배제약정을 하였고, ○○△△병원을 개원한 후 이 사건 병원의 일부 근로자와 환자들을 이전하였으므로, 일부양도에 불과하다고 주장한다."
        ],
        "dedatAssrs": []
    },
    "facts": {
        "bsisFacts": [
            "소외 1은 2015. 9. 1.부터 2015. 11. 30.까지 부산 00군 00읍 (주소 생략)에서 상시근로자 60여 명을 사용하여 □□□요양병원(이하 ‘이 사건 병원’이라 한다)을 운영한 사람이고, 원고는 소외 1로부터 이 사건 병원 영업을 양수한 뒤 2015. 12.1.부터 상시근로자 50여 명을 사용하여 이 사건 병원을 운영하는 사람이다.",
            "소외 2, 소외 3, 소외 4(이하 순차적으로 ‘이 사건 근로자 1~3’이라 하고, 모두를 지칭할 때에는 ‘이 사건 근로자들’이라 한다)은○○△△요양병원에 입사하여 각 응급차기사, 물리치료실장, 간호조무사로 근무하던 사람이다.",
            "전국보건의료산업노동조합(이하 ‘이 사건 노동조합’이라 한다)은 전국보건의료산업에 종사하는 근로자를 가입대상으로 하여1998. 2. 27. 설립된 산업별 노동조합으로서 이 사건 근로자들은 이 사건 노동조합의 □□□요양병원지부(지부장: 이 사건 근로자1)에 소속되어 있고, 상급단체는 전국민주노동조합총연맹이다.",
            "소외 1은 2015. 9. 1. 이 사건 근로자1, 2의 고용승계를 거부하였고, 2015. 10. 1. 이 사건 근로자3을 해고하였다(이하 ‘이사건 각 해고’라 한다).",
            "이 사건 근로자들은 소외 1이 한 이 사건 각 해고는 부당해고이고, 이 사건 근로자들의 노동조합 활동에 대한 불이익 취급의 부당노동행위라고 주장하며, 2015. 10. 6. 부산지방노동위원회에 구제신청을 하였고, 2015. 12. 10. 원고를 피신청인으로 추가하였다.",
            "부산지방노동위원회는 2015. 12. 29. 이 사건 근로자들 및 이 사건 노동조합의 소외 1에 대한 구제신청은 각하하고, 원고에 대한 구제신청은 기각하였다(부산2015부해642/부노102 병합, 이하 ‘초심판정’이라 한다).",
            "이 사건 근로자들과 이 사건 노동조합은 초심판정에 불복하여 2016. 2. 1. 중앙노동위원회에 재심신청을 하였는데, 중앙노동위원회는 2016. 5. 17. 초심판정 중 원고에 대한 부당해고 및 부당노동행위에 관한 부분을 취소하고, 원고가 소외 1의 영업을양수받으면서 이 사건 근로자들을 고용하지 아니한 것은 부당해고 및 불이익취급의 부당노동행위임을 인정하였다.",
            "원고에게 이사건 근로자들을 원직복직에 갈음하여 금전보상금을 지급하고, 중앙노동위원회로부터 받은 구제명령에 관한 공고문과 재심판정서를 1개월 이상 게시하라는 판정을 하였다(중앙2016부해120/부노22 병합, 이하 ‘이 사건 재심판정’이라 한다)."
        ]
    },
    "dcss": {
        "courtDcss": [
            "영업의 양도라 함은 일정한 영업목적에 의하여 조직화된 업체, 즉 인적·물적 조직을 그 동일성은 유지하면서 일체로서 이전하는것으로서 영업의 일부만의 양도도 가능하고, 이러한 영업양도가 이루어진 경우에는 원칙적으로 해당 근로자들의 근로관계가양수하는 기업에 포괄적으로 승계된다.",
            "여기서 영업의 동일성 여부는 일반 사회관념에 의하여 결정되어져야 할 사실인정의 문제이기는 하지만, 문제의 행위(양도계약관계)가 영업의 양도로 인정되느냐 안되느냐는 단지 어떠한 영업재산이 어느 정도로 이전되어 있는가에 의하여 결정되어져야 하는 것이 아니고 거기에 종래의 영업조직이 유지되어 그 조직이 전부 또는 중요한 일부로서 기능할 수 있는가에 의하여 결정되어져야 하는 것이다.",
            "예컨대 영업재산의 전부를 양도했어도 그 조직을 해체하여 양도했다면 영업의 양도는 되지 않는 반면에 그 일부를 유보한 채 영업시설을 양도했어도 그 양도한 부분만으로도 종래의 조직이 유지되어 있다고 사회관념상 인정되면 그것을 영업의 양도라 볼 것이다(대법원 2001. 7. 27. 선고 99두2680 판결 등 참조).",
            "소외 5는 소외 1과 계약을 체결하기 전 이 사건 노동조합과 이행각서를 작성하여 직원들의 고용승계를 약정하였고, 소외 1과 임대차계약서를 작성한 날 영업을 양수받을 사용자로부터 고용승계를 획득하였다는 공고문을 이 사건 병원 내에 게시하였다.",
            "소외 5와 소외 1이 작성한 임대차계약서에 의하면 소외 1은 이 사건 병원 전체 장소 및 집기를 일체 임차하는 것으로 약정하였고, ○○△△요양병원의 근로자들 중 66명의 근로가 승계되었으며, 특히 ○○△△요양병원의 원무과장인 소외 7 역시 이 사건 병원으로 고용이 승계되었다.",
            "소외 5는 2014. 1. 2.부터 요양병원인 ○○△△요양병원을 개업하여 운영하여 왔는데, 소외 1도 소외 5로부터 위 병원의 영업에 필요한 유형적·무형적 재산을 양수하여 소외 5가 영위하던 요양병원 영업의 동일성을 유지한 채 운영을 계속하였다.",
            "소외 1이 소외 5로부터 영업을 양수하면서 총무, 원무, 행정 등 업무지원파트와 물리치료실 실장, 임상병리실 실장, 방사선실실장에 대한 고용승계를 배제하기로 약정하여 ○○△△요양병원과 이 사건 병원의 인적 구성의 일부가 변화가 있었다고 하더라도 기본적으로 요양병원으로서 기능을 유지하기 위하여 사회통념상 필요한 간호인력 등의 기본인력은 그대로 유지되었다고 봄이 상당하다.",
            "소외 5는 2015. 8. 26. 소외 1에게 임대형식으로 ○○△△요양병원의 전체 장소 및 집기를 일체 양도하였고, 이후 이 사건 병원에서 근무하다가 2015. 9. 24. 부산 ○○군 ○○읍 (주소 2 생략)에 일반병원인 ○○△△병원을 새로 개원하였다.",
            "소외 5가 이 사건 병원에서 ○○△△병원으로 환자나 근로자를 일부 이전하였다고 하더라도 소외 5의 ○○△△병원 개원 전후로 이 사건 병원 영업의 동일성에 변화가 있었다고 볼 수 없다.",
            "소외 5와 소외 1 사이에 체결한 계약서에 의하더라도 소외 5가 ○○△△요양병원 중 자신이 개원할 일반병원인 ○○△△병원의영업부문과 요양병원인 이 사건 병원의 영업부문을 나누어 요양병원에 해당하는 영업부문만을 소외 1에게 양도하기로 하였다고인정할만한 내용이 없고, 달리 위와 같은 사실을 추인할만한 사정도 인정되지 아니한다.",
            "요양병원 역시 일반병원과 같이 총무, 원무, 행정 등 업무지원파트와 물리치료실, 임상병리실, 방사선실에서 근무하는 인력이필요하다고 봄이 상당함에도 소외 1은 소외 5로부터 이 사건 병원 영업을 양수하면서 총무, 원무, 행정 등 업무지원파트와 물리치료실 실장, 임상병리실 실장, 방사선실 실장에 대한 고용승계를 배제하기로 약정하였다.",
            "위 고용승계 배제의 정당성을 판단하는 것은 별론으로 하더라도 위와 같이 고용승계를 배제한 점만으로 소외 5가 고용승계를 배제한 업무 부문을 자신이 개원할 ○○요양병원으로 이전하기 위하여 소외 1에게 양도하지 않은 것이라고 추인하기 어렵다.",
            "영업이 양도되면 반대의 특약이 없는 한 양도인과 근로자 사이의 근로관계는 원칙적으로 양수인에게 포괄적으로 승계되고, 영업양도 당사자 사이에 근로관계의 일부를 승계의 대상에서 제외하기로 하는 특약이 있는 경우에는 그에 따라 근로관계의 승계가이루어지지 않을 수 있으나, 그러한 특약은 실질적으로 해고나 다름이 없으므로 근로기준법 제30조 제1항 소정의 정당한 이유가 있어야 유효하다.",
            "영업양도 그 자체만을 사유로 삼아 근로자를 해고하는 것은 정당한 이유가 있는 경우에 해당한다고 볼 수없다(대법원 2002. 3. 29. 선고 2000두8455 판결 등 참조).",
            "영업이 포괄적으로 양도되면 반대의 특약이 없는 한 양도인과 근로자 간의 관계도 원칙적으로 양수인에게 포괄적으로 승계되어야 하는 바, 영업양도는 단순히 경영주체의 교체에 그 본래의 목적이 있을 뿐이므로 영업양도 당사자가 영업양도의 기회에 편승하여 영업양도 그 자체의 위험부담을 근로자에게 전가할 수 없다.",
            "소외 1과 소외 5는 영업양도로 인하여 원칙적으로 소외 1에게 고용이 승계되어야 할 전체 근로자 중 이 사건 근로자1, 2가 포함되어 있는 업무지원파트와 물리치료실 실장, 임상병리실 실장, 방사선 실장에 대한 고용을 선별적으로 거부하였다.",
            "그런데 위와 같은 고용승계의 거부가 소외 5의 ○○△△병원 개원을 위하여 필요한 인원을 구분하기 위한 것이라거나 근로기준법제23조 제1항에서 규정하는 정당한 이유가 있기 때문이라고 볼만한 자료가 없다.",
            "더욱이 위와 같은 선별적 고용승계가 근로기준법 제24조 제1항 후문의 규정에 따라 ‘경영악화를 방지하기 위한 사업의 양도’로서 긴박한 경영상의 필요가 있는 때에 해당하고 기타 경영상의 이유에 의한 해고의 요건을 갖춘 경우에 해당한다고 단정하기도 어렵다.",
            "이 사건 근로자3은 이 사건 근로자1의 배우자인바, 원고는 이 사건 근로자3이 수습기간 중에 이 사건 근로자1에게 제보하기 위하여 유효기간이 지난 약품을 세팅하여 의료사고를 유발하려 하였다는 사유로 해고예고 없이 해고하였으나, 이 사건 근로자3의 행위가 의료행위 중이 아닌 물품보고 과정에서 발생한 사안이었고, 이 사건 근로자3의 행위로 의료사고가 발생할 가능성이있다는 사유가 해고의 정당한 이유가 될 수 있다고 보기 어렵다.",
            "이 사건 근로자3에 대한 해고 사유 자체도 인정하기 부족한 점, 영업양도가 이루어진 경우 승계되는 근로관계에는 양도인과 근로자들 관계에서 형성된 집단적 근로관계도 포함되고, 노동조합도 양수인 사업장의 노동조합으로 존속한다고 봄이 상당하므로 단체협약상의 권리·의무도 당연히 승계된다(대법원 2002. 3. 26. 선고 2000다3347 판결)고 보아야 할 것이다.",
            "소외 1은 이 사건 노동조합과 소외 5가 체결한 단체협약에규정되어 있는 해고 절차를 거치지 않고 즉시 해고한 점 등을 종합하여 보면, 소외 1이 이 사건 근로자3을 해고한 것도 해고의 절차, 사유, 양정에 있어서 정당하다고 볼 수 없다.",
            "소외 1은 소외 5로부터 이 사건 병원의 영업을 양수한 것이고, 소외 1, 소외 5, 원고의 공동투자자 소외 8이 2015. 11. 17. 체결한 약정서에도 소외 1이 ‘영업양도인’, 소외 8은 ‘영업양수인’이며 이 사건 병원에 대한 임차인의 지위를 소외 1로부터 승계받은 자라고 규정하고 있다.",
            "소외 8은 소외 1과 소외 5 사이의 권리관계 일체 및 이 사건 병원의 의료시설 허가, 영업, 근로관계 일체(재활센터 및 원무과 제외), 이 사건 병원의 시설 및 집기류를 양수하기로 약정하였으므로, 원고가 소외 1로부터 이 사건 병원의 영업을 전부 양수한 것으로 보지 않을 수 없다.",
            "이 사건 근로자들과소외 1 사이에 부당해고 사건이 부산지방노동위원회에서 진행 중인 점을 알고 있었다.",
            "소외 1은 원고에게 이 사건 병원의 영업을 전부 양도한 이후 폐업하였기 때문에, 소외 1에 대하여 부당해고를 다투던 이 사건 근로자들이 이 사건 재심판정을 통하여 부당해고임을 인정받았음에도 구제실익을 인정받지 못하게 되었다.",
            "이러한 경우에 이 사건 병원의 영업을 전부양수한 원고가 영업양도 당시 이 사건 근로자들에 대한 해고가 부당해고인지 여부를 판단할 수 있었는지에 따라서만 원고에 대한 고용승계를 인정한다면 영업양도인과 양수인 사이에 근로자 승계 배제특약 없이 영업양도인이 영업양도 직전에 근로자들을 해고하는 경우 영업양도 방식을 통한 자유로운 해고가 가능하여 근로기준법 제23조 제1항의 해고사유를 제한하는 입법취지를 잠탈하게 되는 결과가 초래되어 부당하다.",
            "원고는 소외 1로부터 이 사건 병원의 영업을 양도받아 개시하기 전에 이 사건 노동조합으로부터 소외 1이 단체협약 및 근로관계승계에 대하여 책임을 충실히 이행하지 않아 법적인 다툼이 진행 중인 점을 고지받았고, 이 사건 병원의 영업이 소외 5, 소외 1,원고에게로 순차적으로 양도되는 동안 이 사건 병원의 행정업무는 소외 7이 계속 담당하여 왔다.",
            "원고 역시 이사건 근로자들이 이 사건 노동조합의 간부로서 이 사건 병원의 사용자들과 갈등이 있어왔고 이로 인하여 고용승계가 거부되거나 해고된 사실을 인지할 수 있었다고 보인다.",
            "이 사건 근로자들이 이 사건 병원과 부당해고와 관련하여 다툼이 있었던 점 등을 인지하고 있었던 이상, 원고가 이 사건 병원 영업을 양수하면서 이 사건 노동조합의 간부들인 이 사건 근로자들의 고용승계를 거부한 것은 이 사건 근로자들이 노동조합에 가입하였다는 이유 등으로 그 근로자를 해고하거나 그 근로자에게 불이익을 주는 행위에 해당한다고 볼 수 있다."
        ]
    },
    "close": {
        "cnclsns": [
            "원고의 청구를 기각한다.",
            "소송비용은 원고가 부담한다."
        ]
    }
}