{
    "info": {
        "caseField": "3",
        "detailField": "5",
        "trailField": "1",
        "caseNm": "법인세부과처분취소",
        "courtNm": "서울행정법원",
        "judmnAdjuDe": "2014. 04. 17.",
        "caseNo": "2013구합59859",
        "relateLaword": [
            "여신전문금융업법 제3조",
            "구 법인세 제18조의2",
            "구 법인세 제18조의3",
            "독점규제 및 공정거래에 관한 법 제2조",
            "독점규제 및 공정거래에 관한 법 시행령 제2조",
            "금융지주회사법 제2조 ",
            "구 금융지주회사법 제2조 ",
            "구 법인세 제18조",
            "구 법인세 시행령 제17조의2"
        ],
        "qotatPrcdnt": []
    },
    "concerned": {
        "acusr": "2",
        "dedat": "3"
    },
    "org": {
        "orgJdgmnCourtNm": "",
        "orgJdgmnAdjuDe": "",
        "orgJdgmnCaseNo": ""
    },
    "disposal": {
        "disposalform": "10",
        "disposalcontent": [
            "원고 주장과 같이  일반법인의 자회사가 기관투자자에 해당하는 경우 만 익금불산입액에 포함하고자 한다면, 해당 부분만 제18조의3 제1항 4호 단서로 추가로 규정하면 될 뿐이다. 준용될 여지가 없는 가, 나목까지 함께 포함하여 규정하고 있는 제18조의2 제1항 4호의 규정을 준용한다고 할 이유가 없다. 원고의 청구를 기각한다.",
            "소송비용은 원고가 부담한다."
        ]
    },
    "mentionedItems": {
        "rqestObjet": [
            "피고가 2012. 8. 6. 원고에 대하여 한 2008. 4. 1.부터 2009. 3. 31.까지 사업연도 법인세 1,678,255,740원의 부과처분 중 6,163,370원을 초과하는 부분을 취소한다."
        ]
    },
    "assrs": {
        "acusrAssrs": [
            "일반법인 수입배당금 익금불산입액을 계산할 때에도 법 제18조의2 제1항 제4호 단서에 따라 기관투자자인 OOO이 계열회사에 재출자한 금액을 수입배당금 익금불산입액에 포함하여야 한다."
        ],
        "dedatAssrs": [
            "원고에 대하여 2008. 4. 1.부터 2009. 3. 31.까지 사업연도 법인세 1,678,255,740원의 부과처분한다."
        ]
    },
    "facts": {
        "bsisFacts": [
            "원고는 1997. 6. 4. 설립되어 신기술사업자에 대한 투자 등을 하는데, 1999. 11. 12. 여신전문금융업법 제3조 제1항에 의하여 금융위원회에 신기술사업금융업 등록을 하였다.",
            "원고는 000(이하 'OOO'이라고만 한다)의 지분을 보유하고 있다. 원고는 2007년 및 2008년에 000으로부터 22,128,973,500원의 배당금을 수령하였다.",
            "서울지방국세청장은 원고에 대한 법인세 통합조사를 실시하고, 원고가 지주회사가 아닌 법인이어서 법 제18조의2 제1항 제4호 단서 규정을 적용할 수 없고, 같은 법 제18조의3 제1항 제4호에 따라 재출자액도 차감금액이라고 판단하고, 익금불산입액을 재계산하여 피고에게 통보하였다."
        ]
    },
    "dcss": {
        "courtDcss": [
            "이와 같이 법 제18조의2 제1항 제4호 단서 가, 나, 다목은 독점규제법, 금융지주회사법상의 자회사가 손자회사에 출자하거나, 금융지주회사법상의 자회사가 기관투자자인 경우에 한하여 재출자액을 익금불산입액에서 차감하는 것을 제외하도록 규정하고 있다.",
            "원고 주장과 같이 '일반법인의 자회사가 기관투자자에 해당하는 경우'만 익금불산입액에 포함하고자 한다면, 해당 부분만 제18조의3 제1항 4호 단서로 추가로 규정하면 될 뿐이다."
        ]
    },
    "close": {
        "cnclsns": [
            "원고의 청구를 기각한다.",
            "소송비용은 원고가 부담한다."
        ]
    }
}