{
    "info": {
        "caseField": "2",
        "detailField": "6",
        "trailField": "1",
        "caseNm": "폭행",
        "courtNm": "서울중앙지방법원",
        "judmnAdjuDe": "2020. 12. 18.",
        "caseNo": "2020고정1686",
        "relateLaword": [
            "형법 제260조 ",
            "형사소송법 제327조 "
        ],
        "qotatPrcdnt": []
    },
    "concerned": {
        "acusr": "4",
        "dedat": "1"
    },
    "org": {
        "orgJdgmnCourtNm": "",
        "orgJdgmnAdjuDe": "",
        "orgJdgmnCaseNo": ""
    },
    "disposal": {
        "disposalform": "10",
        "disposalcontent": [
            "이 사건 공소가 제기된 후인 2020.12.18. 피해자가 이 법원에 증인으로 출석하여 피고인에 대한 처벌을 희망하지 않는다는 의사를 표시하였으므로, 이 사건 공소를 기각한다."
        ]
    },
    "mentionedItems": {
        "rqestObjet": [
            "피고인은 피해자를 폭행하였다."
        ]
    },
    "assrs": {
        "acusrAssrs": [],
        "dedatAssrs": []
    },
    "facts": {
        "bsisFacts": [
            "피고인은 2020. 5. 24. 00:00경 0000에 있는 C 식당 앞 노상에서 피해자 D(남, 46세)이 식당 안으로 들어서자 아무런 이유 없이 양손으로 피해자의 가슴 부위를 2~3회 밀쳐 피해자를 폭행하였다."
        ]
    },
    "dcss": {
        "courtDcss": [
            "이는 형법 제260조 제1항에 해당하는 죄로서 같은 조 제3항에 따라 피해자의 명시한 의사에 반하여 공소를 제기할 수 없는 사건이다. ",
            "그런데 이 사건 공소가 제기된 후인 2020. 12. 18. 피해자가 이 법원에 증인으로 출석하여 피고인에 대한 처벌을 희망하지 않는다는 의사를 표시하였다.",
            "따라서 형사소송법 제327조 제6호를 적용하여 이 사건 공소를 기각한다."
        ]
    },
    "close": {
        "cnclsns": [
            "이 사건 공소를 기각한다. "
        ]
    }
}