{
    "info": {
        "caseField": "2",
        "detailField": "6",
        "trailField": "2",
        "caseNm": "횡령(예비적죄명:배임)",
        "courtNm": "수원지방법원",
        "judmnAdjuDe": "2011. 01. 11.",
        "caseNo": "2010노4815",
        "relateLaword": [
            "형사소송법 제325조",
            "형사소송법 제364조"
        ],
        "qotatPrcdnt": [
            "대법원 2000. 3. 24. 선고 98도4347 판결",
            "대법원 2002. 4. 12. 선고 2001도2785 판결"
        ]
    },
    "concerned": {
        "acusr": "4",
        "dedat": "1"
    },
    "org": {
        "orgJdgmnCourtNm": "수원지방법원",
        "orgJdgmnAdjuDe": "2010.9.29.",
        "orgJdgmnCaseNo": "2009고단3623"
    },
    "disposal": {
        "disposalform": "10",
        "disposalcontent": [
            "검사의 항소를 기각한다.",
            "수탁자인 피고인이 신탁 부동산인 이 사건 임야에 관한 소유권이전등기를 마침으로써 피해자에 대한 관계에서도 유효하게 소유권을 취득 하고, 피해자를 위하여 이 사건 임야를 보관하는 지위에 있다고 볼 수 없으므로, 이 사 건 임야를 임의로 처분한 뒤 처분대금을 소비하더라도 횡령죄에 해당한다고 할 수 없 다 할 것이니, 피고인에 대하여 무죄를 선고한 원심판결은 정당하고, 거기에 검사가 주 장하는 바와 같은 사실오인 또는 법리오해의 위법이 없다."
        ]
    },
    "mentionedItems": {
        "rqestObjet": [
            "피고인과 피해자 사이의 관계는 중간생략등기형 명의신탁에 해당하고, 설령 계약명 이의신탁에 해당하더라도 매도인 00가 피고인과 피해자의 명의신탁관계를 알고 있었 던 점, 한편 명의수탁자가 명의신탁을 적극적으로 조장하는 등 불법성이 큰 경우 계약 명의신탁관계에서 매도인이 선의라고 하더라도 횡령죄로 처벌하는 것이 타당한 점 등을 고려할 때, ",
            "피고인이 명의신탁받은 부동산을 임의로 매도한 뒤 피해자의 지분에 상 당하는 돈을 소비한 행위는 횡령죄에 해당하므로, 피고인에 대하여 무죄를 선고한 원 심판결에는 사실오인 또는 법리오해의 위법이 있다."
        ]
    },
    "assrs": {
        "acusrAssrs": [
            "피고인과 피해자 사이의 관계는 중간생략등기형 명의신탁에 해당하고, 설령 계약명 이의신탁에 해당하더라도 매도인 00가 피고인과 피해자의 명의신탁관계를 알고 있었던 점, 한편 명의수탁자가 명의신탁을 적극적으로 조장하는 등 불법성이 큰 경우 계약 명의신탁관계에서 매도인이 선의라고 하더라도 횡령죄로 처벌하는 것이 타당한 점 등을 고려할 때, 피고인이 명의신탁 받은 부동산을 임의로 매도한 뒤 피해자의 지분에 상당하는 돈을 소비한 행위는 횡령죄다.",
            "그러므로, 피고인에 대하여 무죄를 선고한 원심판결에는 사실오인 또는 법리오해의 위법이 있다."
        ],
        "dedatAssrs": []
    },
    "facts": {
        "bsisFacts": [
            "주위적으로, 피고인은 2007. 12. 4. 00에게 이 사건 임야를 매도하여 50%에 해당하는 7, 500만 원을 피해자를 위하여 보관하고 있던 중 3, 500만 원만 지급하고 나머지 4, 000만 원을 지급하지 아니하여 이를 횡령하였다.",
            "예비적으로, 피고인은 피해자로부터 이 사건 임야에 관한 매매를 위임받은 자로 50 % 에 해당하는 7, 500만 원을 반환해 주어야 할 임무가 있음에도, 피해자에게 3, 500만 원만 지급하고 나머지 4, 000만 원을 지급하지 아니함으로써 동액 상당의 이익을 취득 하고 피해자에게 동액 상당의 손해를 가하였다.",
            "피고인은 2005. 3. 23. 00와 이 사건 임야를 매매대금 1억 4, 600만 원에 매수한다는 내용의 매매계약을 체결하였고, 00에게 계약금 1, 500만 원을 지급한 사실을 인정한다.",
            "피고인은 2005. 3. 23. 피해자와 이 사건 임야에 관한 실권리가 피해자에게 있다는 내용의 명의신탁약정을 하면서, 00의 대리인 피고인과 피해자 00을 계약명의인으로 하여, 00가 피해자에게 이 사건 임야를 매매대금 1억 6, 200만 원에 매도한다는 내용의 매매계약서를 작성했다.",
            "피해자는 그 무렵 피고인에 게 이 사건 임야의 매수대금을 지급한 사실, 피고인은 00에게 위 매매계약에 따른 잔금을 지급하고, 00로부터 이 사건 임야의 토지거래허가 관련 서류와 등기이전서 류를 교부받았고, 2005. 6. 23. 이 사건 임야에 관하여 피고인 명의의 소유권이전등기 가 경료된 사실을 인정한다.",
            "피해자는 피고인으로부터 0000 소재 주택에 관한 소유권을 이 전받으면서 피고인에게 이 사건 임야 중 1/2의 권리를 행사하도록 한 사실, 피고인은 2007. 12. 00에게 이 사건 임야를 매매대금 3억 2, 000만 원에 매도하면서, 00과 이 사건 임야의 매매대금 중 양도소득세 및 관련 세금, 대출금 등을 공제한 나머지를 정산하여 지급하기로 하는 약정을 한 사실을 인정한다.",
            "이 사건 임야의 매도 인인 00와 이 사건 임야의 매도를 위해 00를 대리한 00은 \"피해자의 존재는 모르고, 피고인을 이 사건 임야의 매수인으로 알고 있었다\"고 진술하고 있고, 피해자도 \"이 사건 임야의 매수를 피고인 등에게 맡겨 이 사건 임야의 매수과정에 관여하지 않았다\"고 진술하고 있는 점 등을 고려할 때, 이하 다음과 같다.",
            "즉, 피고인은 피해자와 이 사건 임야에 관하여 명의신탁약정을 한 뒤 선의의 매도인인 00로부터 이 사건 임야를 매수하기로 하는 계약명의신탁 관계에 있다.",
            "그러므로, 수탁자인 피고인은 신탁자인 피해자와의 관계에서 신탁부동산의 소유권을 완전히 취득하고, 단지 피해자에 대하여 명의신탁약정의 무효로 인한 매수대금 상당액의 부당이득반환의무만을 부담할 뿐 피고인이 피해자를 위하여 이 사건 임야를 보전, 관리하는 지위에 있다고 볼 수 없다는 이유로, 피고인에 대하여 무죄를 선고하였다."
        ]
    },
    "dcss": {
        "courtDcss": [
            "위 법리에 따라 수탁자인 피고인이 신탁 부동산인 이 사건 임야에 관한 소유권이전등기를 마침으로써 피해자에 대한 관계에서도 유효하게 소유권을 취득하고, 피해자를 위하여 이 사건 임야를 보관하는 지위에 있다고 볼 수 없으므로, 이 사건 임야를 임의로 처분한 뒤 처분대금을 소비하더라도 횡령죄에 해당한다고 할 수 없다 할 것이니, 피고인에 대하여 무죄를 선고한 원심판결은 정당하고, 거기에 검사가 주 장하는 바와 같은 사실오인 또는 법리오해의 위법이 없다.",
            "피해자와의 계약명의신탁의 약정에 따른 피고인의 이 사건 임야에 관한 매도 및 그에 따른 정산업무는 피고인 자신의 사무라 할 것이므로, 이 사건 임야를 매도한 뒤 신탁자인 피해자에게 매매대금 중 일부를 지급하지 않았다하더라도 배임죄가 성립하지 아니한다."
        ]
    },
    "close": {
        "cnclsns": [
            "검사의 항소를 기각한다. "
        ]
    }
}