{
    "info": {
        "caseField": "2",
        "detailField": "6",
        "trailField": "1",
        "caseNm": "사기",
        "courtNm": "서울중앙지방법원",
        "judmnAdjuDe": "2014. 12. 30.",
        "caseNo": "2014고단7893",
        "relateLaword": [
            "형법 제347조",
            "형법 제62조"
        ],
        "qotatPrcdnt": []
    },
    "concerned": {
        "acusr": "4",
        "dedat": "1"
    },
    "org": {
        "orgJdgmnCourtNm": "",
        "orgJdgmnAdjuDe": "",
        "orgJdgmnCaseNo": ""
    },
    "disposal": {
        "disposalform": "8",
        "disposalcontent": [
            "피고인을 징역 4월에 처한다.",
            "다만, 이 판결 확정일로부터 2년간 위 형의 집행을 유예한다."
        ]
    },
    "mentionedItems": {
        "rqestObjet": [
            "피고인을 징역 4월에 처한다. ",
            "다만, 이 판결 확정일로부터 2년가 위 형의 집행을 유예한다. "
        ]
    },
    "assrs": {
        "acusrAssrs": [],
        "dedatAssrs": []
    },
    "facts": {
        "bsisFacts": [
            "피고인은 2013. 5. 15. 0000 C에 있는 D 커피숍에서 피해자 E에게 000 고위직과 유대관계를 맺고 있으니 그들에게 부탁하여 2~3개월 안에 000 블루핸즈 A/S 지정점으로 재선정되게 해주겠다. 라고 거짓말을 하였다. ",
            "피고인은 000 고위직과 유대관계가 없어 피해자가 운영하는 정비공장을 000 블루핸즈 A/S 지정점으로 선정시켜 줄 의사나 능력이 없었다. 피고인은 이에 속은 피해자로부터 접대비 명목으로 2013. 5. 15. 피고인 명의의 000 계좌로 2,000,000원을, 성공사례비 담보 명목으로 2013. 5. 27. 같은 계좌로 15,000,000원을 각각 송금받았다. ",
            "피고인은 위와 같이 피해자를 기망하여 재물을 교부받았다"
        ]
    },
    "dcss": {
        "courtDcss": [
            "범죄사실에 대한 해당법조 및 형의 선택 형법 제347조 제1항(징역형 선택)",
            "집행유예 형법 제62조 제1항 편취금 액수, 편귀금 중 500만원은 변제한 점, 초범인 점 참작하 여 권고형량(6월 내지 1년 6월)보다 낮은 형을 선고하고 형의 집행을 유예함 이상의 이유로 주문과 같이 판결한다."
        ]
    },
    "close": {
        "cnclsns": [
            "피고인을 징역 4월에 처한다",
            "이 판결 확정일로부터 2년간 위 형의 집행을 유예한다."
        ]
    }
}