{
    "info": {
        "caseField": "2",
        "detailField": "6",
        "trailField": "1",
        "caseNm": "야간주거침입절도",
        "courtNm": "수원지방법원",
        "judmnAdjuDe": "2015. 12. 30.",
        "caseNo": "2015고단1698",
        "relateLaword": [
            "형법 제330조",
            "형법 제62조 ",
            "형법 제62조의2",
            "보호관찰 등에 관한 법률 제59조"
        ],
        "qotatPrcdnt": []
    },
    "concerned": {
        "acusr": "4",
        "dedat": "1"
    },
    "org": {
        "orgJdgmnCourtNm": "",
        "orgJdgmnAdjuDe": "",
        "orgJdgmnCaseNo": ""
    },
    "disposal": {
        "disposalform": "6",
        "disposalcontent": [
            "피고인을 징역 1년에 처한다.",
            "다만, 이 판결 확정일로부터 2년간 위 형의 집행을 유예한다.",
            "피고인에게 140시간의 사회봉사를 명한다."
        ]
    },
    "mentionedItems": {
        "rqestObjet": [
            "피고인은 야간에 사람의 주거에 침입하여 피해자의 재물을 절취하였다."
        ]
    },
    "assrs": {
        "acusrAssrs": [],
        "dedatAssrs": []
    },
    "facts": {
        "bsisFacts": [
            "피고인은 2015.8.2.04:30경 0000에 있는 피해자 C의 주거지에 이르러 미리 외우고 있던 비밀번호를 디지털도어락에 입력하여 피해자의 집 현관문을 열고 방 안까지 침입한 다음 그곳에 있는 피해자 소유인 시가 500,000원 상당의 000 스마트폰 1대를 가지고 나왔다.",
            "이로써 피고인은 야간에 사람의 주거에 침입하여 피해자의 재물을 절취하였다."
        ]
    },
    "dcss": {
        "courtDcss": [
            "이 사건 범행을 야간에 피해자가 거주하는 주거에 침입하여 절취 범행을 저지른 것으로 그 죄책이 매우 무거운 점, 피해자로부터 용서받지 못한 점 등은 피고인에게 불리한 정상이다.",
            "피고인이 이 사건 공소사실을 인정하고 재범하지 않을 것을 다짐하는 점, 이 사건 이전에는 처벌받은 전력이 없는 점, 피해품이 피해자에게 반환된 점 등은 피고인에게 유리한 정상으로 각 참작한다.",
            "그밖에 피고인의 나이, 성행, 가정환경 등 기록에 나타난 여러 정상을 참작하여 주문과 같이 판결한다."
        ]
    },
    "close": {
        "cnclsns": [
            "피고인을 징역 1년에 처한다.",
            "다만, 이 판결 확정일로부터 2년간 위 형의 집행을 유예한다.",
            "피고인에게 140시간의 사회봉사를 명한다."
        ]
    }
}